blosc2_openhtj2k-0.1.2.dist-info/RECORD
blosc2_openhtj2k-0.1.2.dist-info/WHEEL
blosc2_openhtj2k-0.1.2.dist-info/entry_points.txt
blosc2_openhtj2k-0.1.2.dist-info/METADATA
blosc2_openhtj2k/__init__.py
blosc2_openhtj2k/libblosc2_openhtj2k.so
blosc2_openhtj2k/.dylibs/liblzma.5.dylib
blosc2_openhtj2k/.dylibs/libjpeg.8.3.2.dylib
blosc2_openhtj2k/.dylibs/libzstd.1.5.5.dylib
blosc2_openhtj2k/.dylibs/libtiff.6.dylib
