Metadata-Version: 2.1
Name: blosc2_openhtj2k
Version: 0.1.2
Summary: Plugin of the OpenHTJ2K codec for the C-Blosc2 library
Keywords: plugin blosc2
Author-Email: Blosc Development Team <blosc@blosc.org>
Maintainer-Email: Blosc Development Team <blosc@blosc.org>
License: BSD-3-Clause
Classifier: Programming Language :: Python :: 3
Classifier: Development Status :: 3 - Alpha
Classifier: Intended Audience :: Developers
Classifier: License :: OSI Approved :: BSD License
Classifier: Topic :: Software Development :: Libraries :: Python Modules
Classifier: Operating System :: Microsoft :: Windows
Classifier: Operating System :: Unix
Classifier: Programming Language :: C
Classifier: Programming Language :: C++
Requires-Dist: blosc2
